<?xml version = '1.0' encoding = 'UTF-8'?>
<Relation class="oracle.dbtools.crest.model.design.logical.Relation" name="Relation_5" directorySegmentName="seg_0" id="1F7913AE-CC36-583C-9665-FE5AEB574173">
<createdBy>matias</createdBy>
<createdTime>2024-08-29 15:48:07 UTC</createdTime>
<ownerDesignName>Modelamiento_Basico_Hotel</ownerDesignName>
<engineerTo>
<item key="83EA667B-59DC-F0C8-C0DB-FC7842ED9B64" value="true"/>
</engineerTo>
<sourcePk>F56BBF69-BEE0-C1BD-B345-D82DB53D71AF</sourcePk>
<identifying>false</identifying>
<optionalSource>true</optionalSource>
<optionalTarget>false</optionalTarget>
<sourceCardinality>1</sourceCardinality>
<sourceEntity>C31CE290-4314-3206-2170-67B5F3998C5E</sourceEntity>
<targetCardinalityString>*</targetCardinalityString>
<targetEntity>0F035075-F453-02E7-C95E-E4021EC2AE15</targetEntity>
<transferable>true</transferable>
<deleteRule>NO ACTION</deleteRule>
</Relation>